dexter/__init__.py
dexter/dexter.py
dexter_encoder-1.0.dist-info/METADATA
dexter_encoder-1.0.dist-info/WHEEL
dexter_encoder-1.0.dist-info/top_level.txt
dexter_encoder-1.0.dist-info/RECORD
