Metadata-Version: 2.1
Name: dexter-encoder
Version: 1.0
Summary: A simple dynamic encoder and decoder with random shifts.
Home-page: https://github.com/Brownpanda29/dexter
Author: Ethan Fraser
Author-email: ethanprime.c137@mail.com
Keywords: python,encoding,decoding,shellcode,security
Classifier: Development Status :: 3 - Alpha
Classifier: Intended Audience :: Developers
Classifier: Topic :: Software Development :: Libraries
Classifier: Programming Language :: Python :: 3
Classifier: License :: OSI Approved :: MIT License
Classifier: Operating System :: OS Independent
Requires-Python: >=3.6
